steren/cli.py
steren/data.py
steren/network.py
steren/networks/YOLOv8.py
steren/networks/__init__.py
steren/networks/slicer.py
steren-0.0.2a0.dist-info/METADATA
steren-0.0.2a0.dist-info/WHEEL
steren-0.0.2a0.dist-info/entry_points.txt
steren-0.0.2a0.dist-info/top_level.txt
steren-0.0.2a0.dist-info/RECORD
