Metadata-Version: 2.4
Name: steren
Version: 0.0.2a0
Summary: A computer vision package for planetary GIS data and using neural networks
Author-email: Jack Rich <j.b.c.rich@pgr.reading.ac.uk>
License: MIT
Requires-Python: >=3.8
Requires-Dist: typer
Requires-Dist: numpy
Requires-Dist: tqdm
Requires-Dist: pyaml
Requires-Dist: requests
Requires-Dist: beautifulsoup4
Requires-Dist: geopandas
Requires-Dist: shapely
Requires-Dist: rasterio
Requires-Dist: opencv-python
Requires-Dist: lxml
